{
  "abp_params": null,
  "adr_algorithm_id": "default",
  "allow_roaming": false,
  "app_layer_params": {
    "ts003_f_port": 202,
    "ts003_version": null,
    "ts004_f_port": 201,
    "ts004_version": null,
    "ts005_f_port": 200,
    "ts005_version": null
  },
  "auto_detect_measurements": true,
  "class_b_params": null,
  "class_c_params": null,
  "description": "",
  "device_status_req_interval": 1,
  "firmware_version": "",
  "flush_queue_on_activate": true,
  "mac_version": "1.0.3",
  "measurements": {
    "alarm": {
      "kind": "STRING",
      "name": "alarm"
    },
    "base_id": {
      "kind": "STRING",
      "name": "base_id"
    },
    "battery_voltage": {
      "kind": "GAUGE",
      "name": "Batterie Volt"
    },
    "co2_ppm": {
      "kind": "GAUGE",
      "name": "CO2 ppm"
    },
    "dew_point": {
      "kind": "STRING",
      "name": "Taupunkt"
    },
    "humidity": {
      "kind": "GAUGE",
      "name": "Luftfeuchtigkeit"
    },
    "internal_temperature": {
      "kind": "GAUGE",
      "name": "interne Temperatur"
    },
    "major_version": {
      "kind": "STRING",
      "name": "Major Version"
    },
    "minor_version": {
      "kind": "STRING",
      "name": "Minor Version"
    },
    "networkBaseType": {
      "kind": "STRING",
      "name": "Network Base Type"
    },
    "networkSubType": {
      "kind": "STRING",
      "name": "Network Sub Type"
    },
    "pressure": {
      "kind": "GAUGE",
      "name": "Druck"
    },
    "product_version": {
      "kind": "STRING",
      "name": "Produkt Version"
    },
    "up_cnt": {
      "kind": "COUNTER",
      "name": "Up Counter"
    }
  },
  "name": "Sentinum Febris",
  "payload_codec_runtime": "JS",
  "reg_params_revision": "A",
  "region": "EU868",
  "region_config_id": null,
  "relay_params": null,
  "rx1_delay": 0,
  "supported_uplink_data_rates": [],
  "supports_class_b": false,
  "supports_class_c": false,
  "supports_otaa": true,
  "tags": {},
  "uplink_interval": 3600,
  "vendor_profile_id": 0
}
